{
    "set": "2",
    "number": 38,
    "fifth": false,
    "rarity": 0,
    "name": "Lesser Spotted Jellyfloat",
    "image": "038_Lesser_Spotted_Jellyfloat.png",
    "class_": 1,
    "type": 0,
    "energy": 3,
    "time": 4,
    "attack": 0,
    "health": 4,
    "additions": [
        false,
        false,
        false,
        false
    ],
    "elements": [],
    "immunities": [],
    "weaknesses": [
        "Ice"
    ],
    "traits": [
        "Up High",
        "Indirect",
        "Passive"
    ],
    "abilities": [
        "Power Suction"
    ],
    "notes": ""
}