{
    "set": "2",
    "number": 77,
    "fifth": false,
    "rarity": 0,
    "name": "Odd Logo Series",
    "image": "077_Odd_Logo_Series.png",
    "cardclass": 4,
    "cardtype": 1,
    "base_energy": 4,
    "base_time": 2,
    "base_attack": 0,
    "base_health": 0,
    "defense": 0,
    "maxcarry": 0,
    "additions": [
        false,
        true,
        false,
        false
    ],
    "elements": [],
    "immunities": [],
    "weaknesses": [],
    "traits": [
        "Debt Treasure"
    ],
    "abilities": [
        "Conjure"
    ],
    "notes": "Chance Weight"
}